dynabench/_init_.py
dynabench/dataset/__init__.py
dynabench/dataset/_base.py
dynabench/dataset/_dataitems.py
dynabench/dataset/_download.py
dynabench/dataset/_dynabench.py
dynabench/dataset/_equation.py
dynabench/dataset/transforms.py
dynabench/equation.py
dynabench/grid.py
dynabench/initial.py
dynabench/model/__init__.py
dynabench/model/_grid/_neural_operator.py
dynabench/model/_grid/cnn.py
dynabench/model/_grid/neuralpde.py
dynabench/model/_grid/resnet.py
dynabench/model/grind.py
dynabench/model/point/_fno.py
dynabench/model/point/point_transformer/__init__.py
dynabench/model/point/point_transformer/_utils.py
dynabench/model/point/point_transformer/_utilsv3.py
dynabench/model/point/point_transformer/_v1.py
dynabench/model/point/point_transformer/_v3.py
dynabench/model/utils.py
dynabench/solver/__init__.py
dynabench/solver/_base.py
dynabench/solver/_dedalus.py
dynabench/solver/_diff.py
dynabench/solver/_pypde.py
dynabench/utils/animation.py
dynabench/utils/colors.py
dynabench-0.4.4.dist-info/LICENCE
dynabench-0.4.4.dist-info/LICENCE_data
dynabench-0.4.4.dist-info/METADATA
dynabench-0.4.4.dist-info/WHEEL
dynabench-0.4.4.dist-info/RECORD
