Metadata-Version: 2.3
Name: dynabench
Version: 0.4.4
Summary: Benchmark dataset for learning dynamical systems from data
License: MIT
Author: Andrzej Dulny
Author-email: andzej.dulny@gmail.com
Requires-Python: >=3.10,<3.14
Classifier: License :: OSI Approved :: MIT License
Classifier: Programming Language :: Python :: 3
Classifier: Programming Language :: Python :: 3.10
Classifier: Programming Language :: Python :: 3.11
Classifier: Programming Language :: Python :: 3.12
Classifier: Programming Language :: Python :: 3.13
Requires-Dist: einops (>=0.8.1,<0.9.0)
Requires-Dist: h5py (>=3.11.0,<4.0.0)
Requires-Dist: joblib (>=1.4.2,<2.0.0)
Requires-Dist: matplotlib (>=3.8,<4.0)
Requires-Dist: numpy (>=1.26.4)
Requires-Dist: py-pde (>=0.44.0,<0.45.0)
Requires-Dist: requests (>=2.31.0,<3.0.0)
Requires-Dist: sympy (>=1.12,<2.0)
Requires-Dist: torch (>=2.3.0,<3.0.0)
Requires-Dist: torchdiffeq (>=0.2.3,<0.3.0)
Requires-Dist: tqdm (>=4.66.2,<5.0.0)
Project-URL: Documentation, https://dynabench.github.io/
Project-URL: Homepage, https://dynabench.github.io/about.html
Project-URL: Repository, https://github.com/badulion/dynabench/
